{
  "subjects": [
    {
      "rate": "9.6",
      "cover_x": 880,
      "title": "Running Man",
      "url": "https://movie.douban.com/subject/10509888/",
      "playable": false,
      "cover": "https://img3.doubanio.com/view/photo/s_ratio_poster/public/p2512561572.jpg",
      "id": "10509888",
      "cover_y": 1280,
      "is_new": false
    },
    {
      "rate": "9.0",
      "cover_x": 704,
      "title": "孤独的美食家 第一季",
      "url": "https://movie.douban.com/subject/7065168/",
      "playable": true,
      "cover": "https://img3.doubanio.com/view/photo/s_ratio_poster/public/p2135619843.jpg",
      "id": "7065168",
      "cover_y": 1000,
      "is_new": false
    },
    {
      "rate": "9.2",
      "cover_x": 400,
      "title": "极限挑战 第一季",
      "url": "https://movie.douban.com/subject/26387728/",
      "playable": true,
      "cover": "https://img9.doubanio.com/view/photo/s_ratio_poster/public/p2264809475.jpg",
      "id": "26387728",
      "cover_y": 565,
      "is_new": false
    },
    {
      "rate": "8.5",
      "cover_x": 1000,
      "title": "今生是第一次",
      "url": "https://movie.douban.com/subject/27103757/",
      "playable": false,
      "cover": "https://img3.doubanio.com/view/photo/s_ratio_poster/public/p2502013123.jpg",
      "id": "27103757",
      "cover_y": 1425,
      "is_new": false
    },
    {
      "rate": "9.6",
      "cover_x": 600,
      "title": "搞笑一家人",
      "url": "https://movie.douban.com/subject/2360882/",
      "playable": false,
      "cover": "https://img9.doubanio.com/view/photo/s_ratio_poster/public/p2187842414.jpg",
      "id": "2360882",
      "cover_y": 860,
      "is_new": false
    },
    {
      "rate": "9.4",
      "cover_x": 1500,
      "title": "毒枭 第三季",
      "url": "https://movie.douban.com/subject/26869684/",
      "playable": false,
      "cover": "https://img3.doubanio.com/view/photo/s_ratio_poster/public/p2498121123.jpg",
      "id": "26869684",
      "cover_y": 2222,
      "is_new": false
    },
    {
      "rate": "7.9",
      "cover_x": 1080,
      "title": "中间人生",
      "url": "https://movie.douban.com/subject/35048096/",
      "playable": true,
      "cover": "https://img3.doubanio.com/view/photo/s_ratio_poster/public/p2599965892.jpg",
      "id": "35048096",
      "cover_y": 1831,
      "is_new": false
    },
    {
      "rate": "7.2",
      "cover_x": 1142,
      "title": "致我们单纯的小美好",
      "url": "https://movie.douban.com/subject/27008416/",
      "playable": true,
      "cover": "https://img9.doubanio.com/view/photo/s_ratio_poster/public/p2503805665.jpg",
      "id": "27008416",
      "cover_y": 1600,
      "is_new": false
    },
    {
      "rate": "9.3",
      "cover_x": 674,
      "title": "抽象：设计的艺术 第二季",
      "url": "https://movie.douban.com/subject/34840075/",
      "playable": false,
      "cover": "https://img3.doubanio.com/view/photo/s_ratio_poster/public/p2569563810.jpg",
      "id": "34840075",
      "cover_y": 1000,
      "is_new": false
    },
    {
      "rate": "8.8",
      "cover_x": 2215,
      "title": "风筝",
      "url": "https://movie.douban.com/subject/25752323/",
      "playable": true,
      "cover": "https://img9.doubanio.com/view/photo/s_ratio_poster/public/p2508082006.jpg",
      "id": "25752323",
      "cover_y": 3101,
      "is_new": false
    },
    {
      "rate": "8.3",
      "cover_x": 1000,
      "title": "双层公寓：东京2019-2020",
      "url": "https://movie.douban.com/subject/33404714/",
      "playable": false,
      "cover": "https://img3.doubanio.com/view/photo/s_ratio_poster/public/p2554544310.jpg",
      "id": "33404714",
      "cover_y": 1413,
      "is_new": false
    },
    {
      "rate": "7.6",
      "cover_x": 5967,
      "title": "天坑鹰猎",
      "url": "https://movie.douban.com/subject/27119802/",
      "playable": true,
      "cover": "https://img3.doubanio.com/view/photo/s_ratio_poster/public/p2533751482.jpg",
      "id": "27119802",
      "cover_y": 8533,
      "is_new": false
    },
    {
      "rate": "7.0",
      "cover_x": 523,
      "title": "周游记",
      "url": "https://movie.douban.com/subject/34840740/",
      "playable": true,
      "cover": "https://img9.doubanio.com/view/photo/s_ratio_poster/public/p2593832025.jpg",
      "id": "34840740",
      "cover_y": 929,
      "is_new": false
    },
    {
      "rate": "9.6",
      "cover_x": 640,
      "title": "局部 第一季",
      "url": "https://movie.douban.com/subject/26425522/",
      "playable": true,
      "cover": "https://img9.doubanio.com/view/photo/s_ratio_poster/public/p2253249056.jpg",
      "id": "26425522",
      "cover_y": 1136,
      "is_new": false
    },
    {
      "rate": "8.5",
      "cover_x": 2362,
      "title": "琅琊榜之风起长林",
      "url": "https://movie.douban.com/subject/26665065/",
      "playable": true,
      "cover": "https://img9.doubanio.com/view/photo/s_ratio_poster/public/p2503635995.jpg",
      "id": "26665065",
      "cover_y": 3321,
      "is_new": false
    },
    {
      "rate": "8.9",
      "cover_x": 600,
      "title": "玛嘉烈与大卫  绿豆",
      "url": "https://movie.douban.com/subject/26742360/",
      "playable": true,
      "cover": "https://img1.doubanio.com/view/photo/s_ratio_poster/public/p2332500589.jpg",
      "id": "26742360",
      "cover_y": 850,
      "is_new": false
    },
    {
      "rate": "8.1",
      "cover_x": 1049,
      "title": "向往的生活 第二季",
      "url": "https://movie.douban.com/subject/27602222/",
      "playable": true,
      "cover": "https://img9.doubanio.com/view/photo/s_ratio_poster/public/p2520109024.jpg",
      "id": "27602222",
      "cover_y": 1468,
      "is_new": false
    },
    {
      "rate": "9.6",
      "cover_x": 1024,
      "title": "局部 第三季",
      "url": "https://movie.douban.com/subject/33406300/",
      "playable": true,
      "cover": "https://img3.doubanio.com/view/photo/s_ratio_poster/public/p2579391183.jpg",
      "id": "33406300",
      "cover_y": 1820,
      "is_new": false
    },
    {
      "rate": "6.0",
      "cover_x": 1080,
      "title": "下一站是幸福",
      "url": "https://movie.douban.com/subject/30176770/",
      "playable": true,
      "cover": "https://img3.doubanio.com/view/photo/s_ratio_poster/public/p2581584771.jpg",
      "id": "30176770",
      "cover_y": 1620,
      "is_new": false
    },
    {
      "rate": "8.7",
      "cover_x": 1773,
      "title": "请回答1994",
      "url": "https://movie.douban.com/subject/24759014/",
      "playable": true,
      "cover": "https://img9.doubanio.com/view/photo/s_ratio_poster/public/p2157182676.jpg",
      "id": "24759014",
      "cover_y": 2508,
      "is_new": false
    }
  ]
}